MANIFEST.in
README.md
setup.py
flask_admin_dashboard/__init__.py
flask_admin_dashboard/admin_dashboard.py
flask_admin_dashboard/models.py
flask_admin_dashboard.egg-info/PKG-INFO
flask_admin_dashboard.egg-info/SOURCES.txt
flask_admin_dashboard.egg-info/dependency_links.txt
flask_admin_dashboard.egg-info/entry_points.txt
flask_admin_dashboard.egg-info/not-zip-safe
flask_admin_dashboard.egg-info/requires.txt
flask_admin_dashboard.egg-info/top_level.txt
flask_admin_dashboard/scripts/__init__.py
flask_admin_dashboard/scripts/cli.py
flask_admin_dashboard/static/assets/Eo_circle_green_checkmark.svg.png
flask_admin_dashboard/static/css/admin.css
flask_admin_dashboard/static/css/login.css
flask_admin_dashboard/static/css/main.css
flask_admin_dashboard/static/js/codemirror.js
flask_admin_dashboard/templates/admin/authorization_status.html
flask_admin_dashboard/templates/admin/index.html
flask_admin_dashboard/templates/admin/logs.html
flask_admin_dashboard/templates/admin/master.html
flask_admin_dashboard/templates/admin/token_edit.html
flask_admin_dashboard/templates/admin/tokens.html
flask_admin_dashboard/templates/security/login.html
flask_admin_dashboard/utilities/__init__.py
flask_admin_dashboard/utilities/cache.py
flask_admin_dashboard/utilities/jsonhandler.py
flask_admin_dashboard/utilities/timehandler.py
flask_admin_dashboard/views/__init__.py
flask_admin_dashboard/views/auth.py
flask_admin_dashboard/views/logs.py