Metadata-Version: 2.1
Name: flask-admin-dashboard
Version: 1.0.6
Summary: Admin Dashboard for Flask
Home-page: https://bitbucket.org/theapiguys/flask_admin_dashboard
Author: Will @ TheAPIGuys
Author-email: will@theapiguys.com
License: UNKNOWN
Platform: UNKNOWN
